promptscan_sdk-0.1.1.dist-info/METADATA
promptscan_sdk-0.1.1.dist-info/WHEEL
promptscan_sdk-0.1.1.dist-info/entry_points.txt
promptscan_sdk-0.1.1.dist-info/licenses/LICENCE
promptscan_sdk/__init__.py
promptscan_sdk/client/__init__.py
promptscan_sdk/client/api_key.py
promptscan_sdk/client/async_base_client.py
promptscan_sdk/client/base_client.py
promptscan_sdk/client/base_model.py
promptscan_sdk/client/client.py
promptscan_sdk/client/collect_generations.py
promptscan_sdk/client/enums.py
promptscan_sdk/client/exceptions.py
promptscan_sdk/client/input_types.py
promptscan_sdk/sdk.py
promptscan_sdk/utils.py
promptscan_sdk-0.1.1.dist-info/RECORD
