Metadata-Version: 2.1
Name: promptscan-sdk
Version: 0.1.1
Author-Email: Bogdan Sulima <bogdan.sulima@promptscan.ai>
Classifier: Programming Language :: Python :: 3
Classifier: Programming Language :: Python :: 3.9
Classifier: Programming Language :: Python :: 3.10
Classifier: Programming Language :: Python :: 3.11
Classifier: Programming Language :: Python :: 3.12
Classifier: Programming Language :: Python :: 3.13
Classifier: License :: OSI Approved :: MIT License
Classifier: Operating System :: OS Independent
Classifier: Development Status :: 4 - Beta
Classifier: Intended Audience :: Developers
Classifier: Topic :: Software Development :: Libraries :: Python Modules
Project-URL: Homepage, https://github.com/promptscan/sdk-python
Project-URL: Issues, https://github.com/promptscan/sdk-python/issues
Requires-Python: >=3.9
Requires-Dist: pydantic>=2
Requires-Dist: python-dateutil==2.9.0
Requires-Dist: httpx<1.0,>=0.27
Provides-Extra: test
Requires-Dist: pytest==8.3.1; extra == "test"
Requires-Dist: pytest-asyncio==0.23.8; extra == "test"
Requires-Dist: pytest-dotenv==0.5.2; extra == "test"
Requires-Dist: pytest-recording==0.13.2; extra == "test"
Requires-Dist: pytest-sugar==1.0.0; extra == "test"
Requires-Dist: vcrpy==6.0.1; extra == "test"
Requires-Dist: openai==1.55.1; extra == "test"
Provides-Extra: dev
Requires-Dist: ariadne-codegen==0.14.0; extra == "dev"
